vineyardutils/__init__.py
vineyardutils/datasampler.py
vineyardutils/elevation.py
vineyardutils/kmlutils.py
vineyardutils-1.0.dist-info/LICENSE
vineyardutils-1.0.dist-info/METADATA
vineyardutils-1.0.dist-info/WHEEL
vineyardutils-1.0.dist-info/top_level.txt
vineyardutils-1.0.dist-info/RECORD
