Metadata-Version: 2.1
Name: vineyardutils
Version: 1.0
Summary: A Python package for digital agriculture in vineyard-related activities
Home-page: https://github.com/pierluigirossi86/VineyardUtils
Author: Pierluigi Rossi
Author-email: Pierluigi Rossi <pierluigi.rossi@unitus.it>
License: MIT
Project-URL: Homepage, https://github.com/pierluigirossi86/VineyardUtils
Project-URL: Issues, https://github.com/pierluigirossi86/VineyardUtils/issues
Classifier: Programming Language :: Python :: 3
Classifier: License :: OSI Approved :: MIT License
Classifier: Operating System :: OS Independent
Requires-Python: >=3.6
License-File: LICENSE
